[
  {
    "name": "Fireworm",
    "img": "https://static.wikia.nocookie.net/howtotrainyourdragon/images/2/23/Fireworm_Queen_0.5.png",
    "origin": "Dragons: Riders of Berk",
    "class": "Stoker"
  },
  {
    "name": "Flame Whipper",
    "img": "https://static.wikia.nocookie.net/howtotrainyourdragon/images/0/0a/Flame_Whipper_Transparent.png",
    "origin": "School of Dragons",
    "class": "Stoker"
  },
  {
    "name": "Gobsucker",
    "img": "https://static.wikia.nocookie.net/howtotrainyourdragon/images/1/16/1481796977322.png",
    "origin": "Dragons: Rise of Berk",
    "class": "Stoker"
  },
  {
    "name": "Green Death",
    "img": "https://static.wikia.nocookie.net/howtotrainyourdragon/images/5/51/Green_Death_%28from_School_of_Dragons%29.png",
    "origin": "Dragons: Rise of Berk",
    "class": "Stoker"
  },
  {
    "name": "Hobblegrunt",
    "img": "https://static.wikia.nocookie.net/howtotrainyourdragon/images/5/5e/1481251229305.png",
    "origin": "How To Train Your Dragon 2",
    "class": "Stoker"
  },
  {
    "name": "Hobgobbler",
    "img": "https://static.wikia.nocookie.net/howtotrainyourdragon/images/5/50/THW-Hobgobbler-Transparent.png",
    "origin": "The Hidden World",
    "class": "Stoker"
  },
  {
    "name": "Large Shadow Wing",
    "img": "https://static.wikia.nocookie.net/howtotrainyourdragon/images/5/5a/ShadowWing456.png",
    "origin": "Dragons: Race to the Edge",
    "class": "Stoker"
  },
  {
    "name": "Monstrous Nightmare",
    "img": "https://static.wikia.nocookie.net/howtotrainyourdragon/images/5/56/1481529221423.png",
    "origin": "How To Train Your Dragon",
    "class": "Stoker"
  },
  {
    "name": "Night Terror",
    "img": "https://static.wikia.nocookie.net/howtotrainyourdragon/images/d/d6/Nightterror_infobox.png",
    "origin": "Dragons: Race to the Edge",
    "class": "Stoker"
  },
  {
    "name": "Red Death",
    "img": "https://static.wikia.nocookie.net/howtotrainyourdragon/images/e/e4/Red_Death_flying_%28transparent%29.png",
    "origin": "How To Train Your Dragon",
    "class": "Stoker"
  },
  {
    "name": "Silver Phantom",
    "img": "https://static.wikia.nocookie.net/howtotrainyourdragon/images/d/db/PicsArt_12-19-09.10.13.png",
    "origin": "School of Dragons",
    "class": "Stoker"
  },
  {
    "name": "Singetail",
    "img": "https://static.wikia.nocookie.net/howtotrainyourdragon/images/3/32/Imagen1gh.png",
    "origin": "Dragons: Race to the Edge",
    "class": "Stoker"
  },
  {
    "name": "Small Shadow Wing",
    "img": "https://static.wikia.nocookie.net/howtotrainyourdragon/images/2/21/Small_Shadow_Render.png",
    "origin": "Dragons: Race to the Edge",
    "class": "Stoker"
  },
  {
    "name": "Terrible Terror",
    "img": "https://static.wikia.nocookie.net/howtotrainyourdragon/images/2/2c/1481530669268.png",
    "origin": "How To Train Your Dragon",
    "class": "Stoker"
  },
  {
    "name": "Threadtail",
    "img": "https://static.wikia.nocookie.net/howtotrainyourdragon/images/b/bd/Threadtail_-_NBG.png",
    "origin": "How To Train Your Dragon 2",
    "class": "Stoker"
  },
  {
    "name": "Typhoomerang",
    "img": "https://static.wikia.nocookie.net/howtotrainyourdragon/images/9/95/1481264040302.png",
    "origin": "Dragons: Riders of Berk",
    "class": "Stoker"
  }
]
